hh_mcp_comfyui/__init__.py
hh_mcp_comfyui/__main__.py
hh_mcp_comfyui/comfyui_client.py
hh_mcp_comfyui/server.py
hh_mcp_comfyui-2025.7.1.1.dist-info/METADATA
hh_mcp_comfyui-2025.7.1.1.dist-info/WHEEL
hh_mcp_comfyui-2025.7.1.1.dist-info/entry_points.txt
hh_mcp_comfyui-2025.7.1.1.dist-info/licenses/LICENSE
hh_mcp_comfyui-2025.7.1.1.dist-info/RECORD
