Metadata-Version: 2.4
Name: hh-mcp-comfyui
Version: 2025.7.1.1
Summary: 基于Model Context Protocol (MCP)的ComfyUI图像生成服务，通过API调用本地ComfyUI实例生成图片,实现自然语言生图自由
Project-URL: Homepage, https://github.com/zjf2671/hh-mcp-comfyui
Project-URL: Repository, https://github.com/zjf2671/hh-mcp-comfyui
Project-URL: Issues, https://github.com/zjf2671/hh-mcp-comfyui/issues
Author-email: harryzhang <hh@harryzhang.site>
Maintainer-email: harryzhang <hh@harryzhang.site>
License: MIT License
License-File: LICENSE
Requires-Python: >=3.12
Requires-Dist: aiofiles>=23.2.1
Requires-Dist: aiohttp>=3.9.5
Requires-Dist: httpx>=0.28.1
Requires-Dist: mcp[cli]>=1.6.0
Requires-Dist: websocket-client>=1.8.0
Requires-Dist: websockets>=15.0.1
